Metadata-Version: 2.4
Name: hdlproto
Version: 0.4.1
Summary: A Python-based HDL design prototyping framework for circuit simulation and verification
Author-email: shntn <qzt112222@nifty.com>
License-Expression: MIT
Project-URL: Homepage, https://github.com/shntn/hdlproto
Classifier: Programming Language :: Python :: 3
Classifier: Operating System :: OS Independent
Requires-Python: >=3.10
License-File: LICENSE.txt
Dynamic: license-file
